callchimp/__init__.py
callchimp/api_client.py
callchimp/api_response.py
callchimp/configuration.py
callchimp/exceptions.py
callchimp/py.typed
callchimp/rest.py
callchimp/api/__init__.py
callchimp/api/calls_api.py
callchimp/api/campaigns_api.py
callchimp/api/lists_api.py
callchimp/api/phone_numbers_api.py
callchimp/api/scripts_api.py
callchimp/api/subscribers_api.py
callchimp/api/supervisors_api.py
callchimp/api/voices_api.py
callchimp/api/webhooks_api.py
callchimp/models/__init__.py
callchimp/models/call_list_response.py
callchimp/models/call_report_request.py
callchimp/models/call_report_response.py
callchimp/models/call_report_response_answered_calls.py
callchimp/models/call_report_response_stats_inner.py
callchimp/models/call_request_by_lead_id.py
callchimp/models/call_request_by_vendor_lead_code.py
callchimp/models/call_response.py
callchimp/models/calls_post_request.py
callchimp/models/campaign_add_super_request.py
callchimp/models/campaign_add_super_response.py
callchimp/models/campaign_find_request.py
callchimp/models/campaign_list_response.py
callchimp/models/campaign_lists_request.py
callchimp/models/campaign_remove_super_request.py
callchimp/models/campaign_remove_super_response.py
callchimp/models/campaign_request.py
callchimp/models/campaign_response.py
callchimp/models/campaign_update_request.py
callchimp/models/campaign_upload_audio_response.py
callchimp/models/inbound_call_list_response.py
callchimp/models/inbound_call_response.py
callchimp/models/inbound_call_response_callchimp_number.py
callchimp/models/inbound_call_response_supervisor.py
callchimp/models/list_find_request.py
callchimp/models/lists_list_response.py
callchimp/models/lists_request.py
callchimp/models/lists_response.py
callchimp/models/model4_xx_response.py
callchimp/models/model4_xx_response_errors_inner.py
callchimp/models/phone_number_list_response.py
callchimp/models/phone_number_response.py
callchimp/models/script_list_response.py
callchimp/models/script_request.py
callchimp-0.1.4.dist-info/LICENSE
callchimp-0.1.4.dist-info/METADATA
callchimp-0.1.4.dist-info/WHEEL
callchimp-0.1.4.dist-info/top_level.txt
callchimp-0.1.4.dist-info/RECORD
