Metadata-Version: 2.1
Name: callchimp
Version: 0.1.4
Summary: Callchimp Python SDK
Home-page: https://github.com/callchimp/python-sdk
Author: Dynopii
Author-email: hello@dynopii.com
Keywords: callchimp,calling,ai,calls,calling-ai,callchimp-ai,ai-tools,dynopii
License-File: LICENSE
Requires-Dist: urllib3 <2.1.0,>=1.25.3
Requires-Dist: python-dateutil
Requires-Dist: pydantic >=2
Requires-Dist: typing-extensions >=4.7.1
